appmaker/appmaker.py
appmaker-0.2.2.dist-info/licenses/LICENSE
appmaker-0.2.2.dist-info/METADATA
appmaker-0.2.2.dist-info/WHEEL
appmaker-0.2.2.dist-info/entry_points.txt
appmaker-0.2.2.dist-info/top_level.txt
appmaker-0.2.2.dist-info/RECORD
