Metadata-Version: 2.4
Name: Appmaker
Version: 0.2.2
Summary: Command line tool to package executable into an .app bundle
Home-page: https://github.com/Pixel-Master/appmaker
Author: Pixel Master
Author-email: 
License: GNU GPL v3.0
Keywords: cmd,executable,macOS
Classifier: Programming Language :: Python :: 3
Classifier: License :: OSI Approved :: GNU General Public License v3 or later (GPLv3+)
Classifier: Operating System :: MacOS
License-File: LICENSE
Dynamic: author
Dynamic: classifier
Dynamic: description
Dynamic: home-page
Dynamic: keywords
Dynamic: license
Dynamic: license-file
Dynamic: summary
